LICENSE
hipo_drf_exceptions/__init__.py
hipo_drf_exceptions/apps.py
hipo_drf_exceptions/exceptions.py
hipo_drf_exceptions/handlers.py
hipo_drf_exceptions/settings.py
hipo_drf_exceptions-0.1.8.dist-info/LICENSE
hipo_drf_exceptions-0.1.8.dist-info/WHEEL
hipo_drf_exceptions-0.1.8.dist-info/METADATA
hipo_drf_exceptions-0.1.8.dist-info/RECORD
