Metadata-Version: 2.1
Name: hipo-drf-exceptions
Version: 0.1.8
Summary: A Django app for returning consistent, verbose and easy to parse error messages on Django Rest Framework backends.
Home-page: https://github.com/hipo/hipo-drf-exceptions
License: Apache-2.0
Keywords: python,django,django rest framework,error handling,exception
Author: Hipo
Author-email: pypi@hipolabs.com
Requires-Python: >=3.5,<4
Classifier: Framework :: Django
Classifier: License :: OSI Approved :: Apache Software License
Classifier: Operating System :: OS Independent
Classifier: Programming Language :: Python
Classifier: Programming Language :: Python :: 3
Classifier: Programming Language :: Python :: 3.5
Classifier: Programming Language :: Python :: 3.6
Classifier: Programming Language :: Python :: 3.7
Classifier: Programming Language :: Python :: 3.8
Classifier: Programming Language :: Python :: 3.9
Classifier: Topic :: Internet :: WWW/HTTP
Classifier: Topic :: Internet :: WWW/HTTP :: Dynamic Content
Classifier: Topic :: Software Development :: Libraries :: Python Modules
Requires-Dist: Django (>=2.2)
Requires-Dist: djangorestframework (>=3.0)
Project-URL: Repository, https://github.com/hipo/hipo-drf-exceptions
